lcd_2parcial.vhdl
library IEEE;
use IEEE.numeric_bit.all;

entity lcd_2parcial is 
port (clk,reset,rs,rw_data: in bit; data: in unsigned(7 downto 0);
     rs_out, rw_out, en: out bit; data_out: out unsigned (7 downto 0));
end lcd_2parcial;

architecture arch of lcd_2parcial is 
signal state: unsigned(2 downto 0) := "000";
signal nextstate: unsigned(2 downto 0);

--signal rs_in,rw_in: bit;
signal data_in: unsigned (7 downto 0);

begin
    en <= clk;
    data_out <= data_in;

    process(state,reset,rs,rw_data,data)
    use STD.TEXTIO.all;
    file fout: TEXT open WRITE_MODE is "output_test.txt";
    variable current_line : line;
    
    begin 
        if state /= "100" then
            rs_out <= '0'; 
            rw_out <= '0';
        end if;
        case state is 
            when "000" =>  -- clear LCD
                data_in <= "00000001";
                nextstate <= "001";
                write(current_line, string'("instr(1)"));
                writeline(fout,current_line);
            when "001" => --function set
                data_in <= "00111000";
                nextstate <= "010";
                write(current_line, string'("instr(56)"));
                writeline(fout,current_line);
            when "010" => -- display on/off control
                data_in <= "00001111";
                nextstate <= "011";
                write(current_line, string'("instr(15)"));
                writeline(fout,current_line);
            when "011" =>
                data_in <= "00000110";
                nextstate <= "100";
                write(current_line, string'("instr(6)"));
                writeline(fout,current_line);
            when "100" =>
                if reset = '0' then nextstate <= "000";
                else 
                    data_in <= data; 
                    rs_out <= rs; 
                    rw_out <= rw_data; 
            
                    if rs = '0' then write(current_line, string'("instr("));
                    else write(current_line, string'("data(")); end if;
                    
                    write(current_line, TO_INTEGER(unsigned(data)));
                    write(current_line,string'(")"));
                    writeline(fout,current_line);
                
                end if;
                
            
            when others => null;
        end case;
    
    end process;


    process(clk)
    begin
    if clk'event and clk = '1' then 
        state<= nextstate;
    end if;
    end process;

end arch;

lcd_2parcial_tb.vhdl
library IEEE;
use IEEE.numeric_bit.all;
use IEEE.std_logic_1164.all;
use IEEE.std_logic_textio.all;

entity lcd_2parcial_tb is 
end lcd_2parcial_tb;

architecture arch of lcd_2parcial_tb is 

component lcd_2parcial is 
port (clk,reset,rs,rw_data: in bit; data: in unsigned(7 downto 0);
     rs_out, rw_out, en: out bit; data_out: out unsigned (7 downto 0));
end component;

signal clk,reset,rs,rw_data: bit := '1'; 
signal data: unsigned(7 downto 0);
signal rs_out, rw_out, en: bit; 
signal data_out: unsigned(7 downto 0);


begin
    UUT : lcd_2parcial port map (clk,reset,rs,rw_data,data,rs_out,rw_out,en,data_out);

    P0: process 
    begin    
    clk <= '0';
    wait for 5 ns;
    clk <= '1'; 
    wait for 5 ns;    
    end process;


    stimulus1: process
    use STD.TEXTIO.all;
    file fin: TEXT open READ_MODE is "input_test.txt";
   
    variable current_read_line: line;
    variable current_read_field1: bit;
    variable current_read_field2: bit;
    variable current_read_field3: bit_vector(7 downto 0);
    variable current_read_field4: bit;
    
    begin 
        wait for 34 ns;
        while(not endfile(fin)) loop
            readline(fin, current_read_line);
            read(current_read_line,current_read_field1);
            read(current_read_line,current_read_field2);
            read(current_read_line,current_read_field3);
            read(current_read_line,current_read_field4);

            rs <= current_read_field1;
            rw_data <= current_read_field2;
            data <= unsigned(current_read_field3);
            reset <= current_read_field4;
           
         wait for 10 ns;
        end loop;
        wait;
    end process;

end arch;

lcd_2parcial_tb.vcd
$date
  Tue May 12 00:09:15 2020
$end
$version
  GHDL v0
$end
$timescale
  1 fs
$end
$scope module standard $end
$upscope $end
$scope module numeric_bit $end
$upscope $end
$scope module std_logic_1164 $end
$upscope $end
$scope module textio $end
$upscope $end
$scope module std_logic_textio $end
$upscope $end
$scope module lcd_2parcial_tb $end
$var reg 1 ! clk $end
$var reg 1 " reset $end
$var reg 1 # rs $end
$var reg 1 $ rw_data $end
$var reg 8 % data[7:0] $end
$var reg 1 & rs_out $end
$var reg 1 ' rw_out $end
$var reg 1 ( en $end
$var reg 8 ) data_out[7:0] $end
$scope module uut $end
$var reg 1 * clk $end
$var reg 1 + reset $end
$var reg 1 , rs $end
$var reg 1 - rw_data $end
$var reg 8 . data[7:0] $end
$var reg 1 / rs_out $end
$var reg 1 0 rw_out $end
$var reg 1 1 en $end
$var reg 8 2 data_out[7:0] $end
$var reg 3 3 state[2:0] $end
$var reg 3 4 nextstate[2:0] $end
$var reg 8 5 data_in[7:0] $end
$upscope $end
$upscope $end
$enddefinitions $end
#0
0!
1"
1#
1$
b00000000 %
0&
0'
0(
b00000001 )
0*
1+
1,
1-
b00000000 .
0/
00
01
b00000001 2
b000 3
b001 4
b00000001 5
#5000000
1!
1(
b00111000 )
1*
11
b00111000 2
b001 3
b010 4
b00111000 5
#10000000
0!
0(
0*
01
#15000000
1!
1(
b00001111 )
1*
11
b00001111 2
b010 3
b011 4
b00001111 5
#20000000
0!
0(
0*
01
#25000000
1!
1(
b00000110 )
1*
11
b00000110 2
b011 3
b100 4
b00000110 5
#30000000
0!
0(
0*
01
#34000000
0$
b01001101 %
0-
b01001101 .
#35000000
1!
1&
1(
b01001101 )
1*
1/
11
b01001101 2
b100 3
b01001101 5
#40000000
0!
0(
0*
01
#44000000
b01101001 %
b01101001 )
b01101001 .
b01101001 2
b01101001 5
#45000000
1!
1(
1*
11
#50000000
0!
0(
0*
01
#54000000
b01100111 %
b01100111 )
b01100111 .
b01100111 2
b01100111 5
#55000000
1!
1(
1*
11
#60000000
0!
0(
0*
01
#64000000
b01110101 %
b01110101 )
b01110101 .
b01110101 2
b01110101 5
#65000000
1!
1(
1*
11
#70000000
0!
0(
0*
01
#74000000
b01100101 %
b01100101 )
b01100101 .
b01100101 2
b01100101 5
#75000000
1!
1(
1*
11
#80000000
0!
0(
0*
01
#84000000
b01101100 %
b01101100 )
b01101100 .
b01101100 2
b01101100 5
#85000000
1!
1(
1*
11
#90000000
0!
0(
0*
01
#94000000
#95000000
1!
1(
1*
11
#100000000
0!
0(
0*
01
#105000000
1!
1(
1*
11
#110000000
0!
0(
0*
01
#115000000
1!
1(
1*
11
#120000000
0!
0(
0*
01
#125000000
1!
1(
1*
11
#130000000
0!
0(
0*
01
#135000000
1!
1(
1*
11
#140000000
0!
0(
0*
01
#145000000
1!
1(
1*
11
#150000000
0!
0(
0*
01
#155000000
1!
1(
1*
11
#160000000
0!
0(
0*
01
#165000000
1!
1(
1*
11
#170000000
0!
0(
0*
01
#175000000
1!
1(
1*
11
#180000000
0!
0(
0*
01
#185000000
1!
1(
1*
11
#190000000
0!
0(
0*
01
#195000000
1!
1(
1*
11
#200000000
0!
0(
0*
01
#205000000
1!
1(
1*
11
#210000000
0!
0(
0*
01
#215000000
1!
1(
1*
11
#220000000
0!
0(
0*
01
